setup.py
distributions/Binomialdistribution.py
distributions/Gaussiandistribution.py
distributions/Generaldistribution.py
distributions/__init__.py
imohgeniusdistributions.egg-info/PKG-INFO
imohgeniusdistributions.egg-info/SOURCES.txt
imohgeniusdistributions.egg-info/dependency_links.txt
imohgeniusdistributions.egg-info/not-zip-safe
imohgeniusdistributions.egg-info/top_level.txt